sayhelloworldcutest/__init__.py
sayhelloworldcutest/main.py
sayhelloworldcutest-0.1.0.dist-info/METADATA
sayhelloworldcutest-0.1.0.dist-info/WHEEL
sayhelloworldcutest-0.1.0.dist-info/top_level.txt
sayhelloworldcutest-0.1.0.dist-info/RECORD
